
[
    {
        "name": "a",
        "lastUpdatedAt": 0
    },
    {
        "name": "abbr",
        "lastUpdatedAt": 0
    },
    {
        "name": "address",
        "lastUpdatedAt": 0
    },
    {
        "name": "area",
        "lastUpdatedAt": 0
    },
    {
        "name": "article",
        "lastUpdatedAt": 0
    },
    {
        "name": "aside",
        "lastUpdatedAt": 0
    },
    {
        "name": "audio",
        "lastUpdatedAt": 0
    },
    {
        "name": "b",
        "lastUpdatedAt": 0
    },
    {
        "name": "base",
        "lastUpdatedAt": 0
    },
    {
        "name": "bdi",
        "lastUpdatedAt": 0
    },
    {
        "name": "bdo",
        "lastUpdatedAt": 0
    },
    {
        "name": "blockquote",
        "lastUpdatedAt": 0
    },
    {
        "name": "body",
        "lastUpdatedAt": 0
    },
    {
        "name": "br",
        "lastUpdatedAt": 0
    },
    {
        "name": "button",
        "lastUpdatedAt": 0
    },
    {
        "name": "canvas",
        "lastUpdatedAt": 0
    },
    {
        "name": "caption",
        "lastUpdatedAt": 0
    },
    {
        "name": "cite",
        "lastUpdatedAt": 0
    },
    {
        "name": "code",
        "lastUpdatedAt": 0
    },
    {
        "name": "col",
        "lastUpdatedAt": 0
    },
    {
        "name": "colgroup",
        "lastUpdatedAt": 0
    },
    {
        "name": "data",
        "lastUpdatedAt": 0
    },
    {
        "name": "datalist",
        "lastUpdatedAt": 0
    },
    {
        "name": "dd",
        "lastUpdatedAt": 0
    },
    {
        "name": "del",
        "lastUpdatedAt": 0
    },
    {
        "name": "details",
        "lastUpdatedAt": 0
    },
    {
        "name": "dfn",
        "lastUpdatedAt": 0
    },
    {
        "name": "dialog",
        "lastUpdatedAt": 0
    },
    {
        "name": "div",
        "lastUpdatedAt": 0
    },
    {
        "name": "dl",
        "lastUpdatedAt": 0
    },
    {
        "name": "dt",
        "lastUpdatedAt": 0
    },
    {
        "name": "em",
        "lastUpdatedAt": 0
    },
    {
        "name": "embed",
        "lastUpdatedAt": 0
    },
    {
        "name": "fieldset",
        "lastUpdatedAt": 0
    },
    {
        "name": "figcaption",
        "lastUpdatedAt": 0
    },
    {
        "name": "figure",
        "lastUpdatedAt": 0
    },
    {
        "name": "footer",
        "lastUpdatedAt": 0
    },
    {
        "name": "form",
        "lastUpdatedAt": 0
    },
    {
        "name": "h1",
        "lastUpdatedAt": 0
    },
    {
        "name": "h2",
        "lastUpdatedAt": 0
    },
    {
        "name": "h3",
        "lastUpdatedAt": 0
    },
    {
        "name": "h4",
        "lastUpdatedAt": 0
    },
    {
        "name": "h5",
        "lastUpdatedAt": 0
    },
    {
        "name": "h6",
        "lastUpdatedAt": 0
    },
    {
        "name": "head",
        "lastUpdatedAt": 0
    },
    {
        "name": "header",
        "lastUpdatedAt": 0
    },
    {
        "name": "hgroup",
        "lastUpdatedAt": 0
    },
    {
        "name": "hr",
        "lastUpdatedAt": 0
    },
    {
        "name": "html",
        "lastUpdatedAt": 0
    },
    {
        "name": "i",
        "lastUpdatedAt": 0
    },
    {
        "name": "iframe",
        "lastUpdatedAt": 0
    },
    {
        "name": "img",
        "lastUpdatedAt": 0
    },
    {
        "name": "input",
        "lastUpdatedAt": 0
    },
    {
        "name": "ins",
        "lastUpdatedAt": 0
    },
    {
        "name": "kbd",
        "lastUpdatedAt": 0
    },
    {
        "name": "label",
        "lastUpdatedAt": 0
    },
    {
        "name": "legend",
        "lastUpdatedAt": 0
    },
    {
        "name": "li",
        "lastUpdatedAt": 0
    },
    {
        "name": "link",
        "lastUpdatedAt": 0
    },
    {
        "name": "main",
        "lastUpdatedAt": 0
    },
    {
        "name": "map",
        "lastUpdatedAt": 0
    },
    {
        "name": "mark",
        "lastUpdatedAt": 0
    },
    {
        "name": "menu",
        "lastUpdatedAt": 0
    },
    {
        "name": "meta",
        "lastUpdatedAt": 0
    },
    {
        "name": "meter",
        "lastUpdatedAt": 0
    },
    {
        "name": "nav",
        "lastUpdatedAt": 0
    },
    {
        "name": "noscript",
        "lastUpdatedAt": 0
    },
    {
        "name": "object",
        "lastUpdatedAt": 0
    },
    {
        "name": "ol",
        "lastUpdatedAt": 0
    },
    {
        "name": "optgroup",
        "lastUpdatedAt": 0
    },
    {
        "name": "option",
        "lastUpdatedAt": 0
    },
    {
        "name": "output",
        "lastUpdatedAt": 0
    },
    {
        "name": "p",
        "lastUpdatedAt": 0
    },
    {
        "name": "param",
        "lastUpdatedAt": 0
    },
    {
        "name": "picture",
        "lastUpdatedAt": 0
    },
    {
        "name": "pre",
        "lastUpdatedAt": 0
    },
    {
        "name": "progress",
        "lastUpdatedAt": 0
    },
    {
        "name": "q",
        "lastUpdatedAt": 0
    },
    {
        "name": "rb",
        "lastUpdatedAt": 0
    },
    {
        "name": "rp",
        "lastUpdatedAt": 0
    },
    {
        "name": "rt",
        "lastUpdatedAt": 0
    },
    {
        "name": "rtc",
        "lastUpdatedAt": 0
    },
    {
        "name": "ruby",
        "lastUpdatedAt": 0
    },
    {
        "name": "s",
        "lastUpdatedAt": 0
    },
    {
        "name": "samp",
        "lastUpdatedAt": 0
    },
    {
        "name": "script",
        "lastUpdatedAt": 0
    },
    {
        "name": "section",
        "lastUpdatedAt": 0
    },
    {
        "name": "select",
        "lastUpdatedAt": 0
    },
    {
        "name": "slot",
        "lastUpdatedAt": 0
    },
    {
        "name": "small",
        "lastUpdatedAt": 0
    },
    {
        "name": "source",
        "lastUpdatedAt": 0
    },
    {
        "name": "span",
        "lastUpdatedAt": 0
    },
    {
        "name": "strong",
        "lastUpdatedAt": 0
    },
    {
        "name": "style",
        "lastUpdatedAt": 0
    },
    {
        "name": "sub",
        "lastUpdatedAt": 0
    },
    {
        "name": "summary",
        "lastUpdatedAt": 0
    },
    {
        "name": "sup",
        "lastUpdatedAt": 0
    },
    {
        "name": "table",
        "lastUpdatedAt": 0
    },
    {
        "name": "tbody",
        "lastUpdatedAt": 0
    },
    {
        "name": "td",
        "lastUpdatedAt": 0
    },
    {
        "name": "template",
        "lastUpdatedAt": 0
    },
    {
        "name": "textarea",
        "lastUpdatedAt": 0
    },
    {
        "name": "tfoot",
        "lastUpdatedAt": 0
    },
    {
        "name": "th",
        "lastUpdatedAt": 0
    },
    {
        "name": "thead",
        "lastUpdatedAt": 0
    },
    {
        "name": "time",
        "lastUpdatedAt": 0
    },
    {
        "name": "title",
        "lastUpdatedAt": 0
    },
    {
        "name": "tr",
        "lastUpdatedAt": 0
    },
    {
        "name": "track",
        "lastUpdatedAt": 0
    },
    {
        "name": "u",
        "lastUpdatedAt": 0
    },
    {
        "name": "ul",
        "lastUpdatedAt": 0
    },
    {
        "name": "var",
        "lastUpdatedAt": 0
    },
    {
        "name": "video",
        "lastUpdatedAt": 0
    },
    {
        "name": "wbr",
        "lastUpdatedAt": 0
    }
]
